{
  "ids": {
    "comment": 1,
    "url": 1,
    "consumer": 1,
    "provider": 39
  },
  "models": {
    "comment": {},
    "url": {},
    "consumer": {},
    "provider": {
      "21": "{\"formal_name\":\"fase\",\"common_name\":\"sdfg\",\"phone_number\":\"string\",\"email_address\":\"string\",\"address\":\"string\",\"event_calendar\":\"string\",\"realm\":\"string\",\"username\":\"sdfg\",\"password\":\"test\",\"emailVerified\":true,\"id\":21}",
      "34": "{\"formal_name\":\"asefe\",\"common_name\":\"asdf\",\"phone_number\":\"string\",\"email_address\":\"string\",\"address\":\"string\",\"event_calendar\":\"string\",\"usage_instructions\":\"asef nfeiened \",\"realm\":\"string\",\"username\":\"asdf\",\"password\":\"test\",\"emailVerified\":true,\"id\":34}",
      "35": "{\"formal_name\":\"asefe\",\"common_name\":\"Mental Health Services\",\"phone_number\":\"string\",\"email_address\":\"string\",\"address\":\"string\",\"event_calendar\":\"string\",\"usage_instructions\":\"asef nfeiened \",\"realm\":\"string\",\"username\":\"Mental Health Services\",\"password\":\"test\",\"emailVerified\":true,\"id\":35}",
      "38": "{\"formal_name\":\"Group Transitional Age Youth\",\"common_name\":\"Social Group TAY\",\"phone_number\":\"string\",\"email_address\":\"string\",\"address\":\"string\",\"event_calendar\":\"string\",\"usage_instructions\":\"Show up on time!\",\"realm\":\"string\",\"username\":\"Social Group TAY\",\"password\":\"test\",\"emailVerified\":true,\"id\":38}"
    }
  }
}